{"@module": "pydefect.analyzer.calc_results", "@class": "CalcResults", "@version": "0.9.12", "structure": {"@module": "pymatgen.core.structure", "@class": "Structure", "charge": 0.0, "lattice": {"matrix": [[4.07544864, -0.0, -0.0], [-0.0, 4.07544864, -0.0], [0.0, 0.0, 4.07544864]], "pbc": [true, true, true], "a": 4.07544864, "b": 4.07544864, "c": 4.07544864, "alpha": 90.0, "beta": 90.0, "gamma": 90.0, "volume": 67.69027417851203}, "properties": {}, "sites": [{"species": [{"element": "Cs", "occu": 1}], "abc": [0.0, 0.0, 0.0], "properties": {}, "label": "Cs", "xyz": [0.0, 0.0, 0.0]}, {"species": [{"element": "Cl", "occu": 1}], "abc": [0.5, 0.5, 0.5], "properties": {}, "label": "Cl", "xyz": [2.03772432, 2.03772432, 2.03772432]}]}, "energy": -6.85375809, "magnetization": 0.0, "potentials": [48.9748, 92.8727], "electronic_conv": true, "ionic_conv": true}