{"@module": "pydefect.corrections.efnv_correction", "@class": "ExtendedFnvCorrection", "@version": "0.9.12", "charge": 1, "point_charge_correction": 0.21868203433873634, "defect_region_radius": 6.11317296, "sites": [{"@module": "pydefect.corrections.efnv_correction", "@class": "PotentialSite", "@version": "0.9.12", "specie": "Cs", "distance": 3.8691548913455276, "potential": -0.0010000000000047748, "pc_potential": null}, {"@module": "pydefect.corrections.efnv_correction", "@class": "PotentialSite", "@version": "0.9.12", "specie": "Cs", "distance": 3.8634310005023322, "potential": 0.01729999999999876, "pc_potential": null}, {"@module": "pydefect.corrections.efnv_correction", "@class": "PotentialSite", "@version": "0.9.12", "specie": "Cs", "distance": 3.8615406498920937, "potential": 0.016199999999997772, "pc_potential": null}, {"@module": "pydefect.corrections.efnv_correction", "@class": "PotentialSite", "@version": "0.9.12", "specie": "Cs", "distance": 5.770162604144065, "potential": 0.13159999999999883, "pc_potential": null}, {"@module": "pydefect.corrections.efnv_correction", "@class": "PotentialSite", "@version": "0.9.12", "specie": "Cs", "distance": 5.774743822674049, "potential": 0.13889999999999958, "pc_potential": null}, {"@module": "pydefect.corrections.efnv_correction", "@class": "PotentialSite", "@version": "0.9.12", "specie": "Cs", "distance": 3.882471210484299, "potential": -0.0012000000000043087, "pc_potential": null}, {"@module": "pydefect.corrections.efnv_correction", "@class": "PotentialSite", "@version": "0.9.12", "specie": "Cs", "distance": 5.7753868811812366, "potential": 0.13749999999999574, "pc_potential": null}, {"@module": "pydefect.corrections.efnv_correction", "@class": "PotentialSite", "@version": "0.9.12", "specie": "Cs", "distance": 5.775362623836358, "potential": 0.13159999999999883, "pc_potential": null}, {"@module": "pydefect.corrections.efnv_correction", "@class": "PotentialSite", "@version": "0.9.12", "specie": "Cs", "distance": 3.9054870197050158, "potential": 0.009799999999998477, "pc_potential": null}, {"@module": "pydefect.corrections.efnv_correction", "@class": "PotentialSite", "@version": "0.9.12", "specie": "Cs", "distance": 5.765351798429584, "potential": 0.12449999999999761, "pc_potential": null}, {"@module": "pydefect.corrections.efnv_correction", "@class": "PotentialSite", "@version": "0.9.12", "specie": "Cs", "distance": 5.766428235791095, "potential": 0.12460000000000093, "pc_potential": null}, {"@module": "pydefect.corrections.efnv_correction", "@class": "PotentialSite", "@version": "0.9.12", "specie": "Cs", "distance": 5.765853312772682, "potential": 0.11929999999999552, "pc_potential": null}, {"@module": "pydefect.corrections.efnv_correction", "@class": "PotentialSite", "@version": "0.9.12", "specie": "Cs", "distance": 7.073467165171044, "potential": 0.1255999999999986, "pc_potential": -0.09179902093151719}, {"@module": "pydefect.corrections.efnv_correction", "@class": "PotentialSite", "@version": "0.9.12", "specie": "Cs", "distance": 7.072087816561226, "potential": 0.12709999999999866, "pc_potential": -0.09176942008801432}, {"@module": "pydefect.corrections.efnv_correction", "@class": "PotentialSite", "@version": "0.9.12", "specie": "Cs", "distance": 5.764793370598498, "potential": 0.12869999999999493, "pc_potential": null}, {"@module": "pydefect.corrections.efnv_correction", "@class": "PotentialSite", "@version": "0.9.12", "specie": "Cs", "distance": 7.072614784866867, "potential": 0.12859999999999872, "pc_potential": -0.09178077067200005}, {"@module": "pydefect.corrections.efnv_correction", "@class": "PotentialSite", "@version": "0.9.12", "specie": "Cs", "distance": 7.076975434413636, "potential": 0.13049999999999784, "pc_potential": -0.09187438094554853}, {"@module": "pydefect.corrections.efnv_correction", "@class": "PotentialSite", "@version": "0.9.12", "specie": "Cs", "distance": 3.8773065848952877, "potential": 0.01379999999999626, "pc_potential": null}, {"@module": "pydefect.corrections.efnv_correction", "@class": "PotentialSite", "@version": "0.9.12", "specie": "Cs", "distance": 5.775527140915321, "potential": 0.12659999999999627, "pc_potential": null}, {"@module": "pydefect.corrections.efnv_correction", "@class": "PotentialSite", "@version": "0.9.12", "specie": "Cs", "distance": 5.765827882138976, "potential": 0.12839999999999918, "pc_potential": null}, {"@module": "pydefect.corrections.efnv_correction", "@class": "PotentialSite", "@version": "0.9.12", "specie": "Cs", "distance": 5.771725841725193, "potential": 0.12140000000000128, "pc_potential": null}, {"@module": "pydefect.corrections.efnv_correction", "@class": "PotentialSite", "@version": "0.9.12", "specie": "Cs", "distance": 7.077428965705895, "potential": 0.12279999999999802, "pc_potential": -0.09188401559244413}, {"@module": "pydefect.corrections.efnv_correction", "@class": "PotentialSite", "@version": "0.9.12", "specie": "Cs", "distance": 7.0824591943412045, "potential": 0.12489999999999668, "pc_potential": -0.09199183348244662}, {"@module": "pydefect.corrections.efnv_correction", "@class": "PotentialSite", "@version": "0.9.12", "specie": "Cs", "distance": 5.782620017950904, "potential": 0.12869999999999493, "pc_potential": null}, {"@module": "pydefect.corrections.efnv_correction", "@class": "PotentialSite", "@version": "0.9.12", "specie": "Cs", "distance": 7.085683519937373, "potential": 0.12480000000000047, "pc_potential": -0.09206068746240428}, {"@module": "pydefect.corrections.efnv_correction", "@class": "PotentialSite", "@version": "0.9.12", "specie": "Cs", "distance": 7.077068112807988, "potential": 0.12539999999999907, "pc_potential": -0.0918763858282333}, {"@module": "pydefect.corrections.efnv_correction", "@class": "PotentialSite", "@version": "0.9.12", "specie": "Cl", "distance": 3.655876873089359, "potential": 0.29129999999999256, "pc_potential": null}, {"@module": "pydefect.corrections.efnv_correction", "@class": "PotentialSite", "@version": "0.9.12", "specie": "Cl", "distance": 6.749607163896627, "potential": 0.31759999999999877, "pc_potential": -0.05209274962314856}, {"@module": "pydefect.corrections.efnv_correction", "@class": "PotentialSite", "@version": "0.9.12", "specie": "Cl", "distance": 3.6563907690713973, "potential": 0.29179999999999495, "pc_potential": null}, {"@module": "pydefect.corrections.efnv_correction", "@class": "PotentialSite", "@version": "0.9.12", "specie": "Cl", "distance": 6.752119788579368, "potential": 0.31810000000000116, "pc_potential": -0.05217932124157933}, {"@module": "pydefect.corrections.efnv_correction", "@class": "PotentialSite", "@version": "0.9.12", "specie": "Cl", "distance": 8.879054122915646, "potential": 0.3563999999999936, "pc_potential": -0.09844350961945214}, {"@module": "pydefect.corrections.efnv_correction", "@class": "PotentialSite", "@version": "0.9.12", "specie": "Cl", "distance": 6.752815344747151, "potential": 0.3178999999999945, "pc_potential": -0.05214930395954099}, {"@module": "pydefect.corrections.efnv_correction", "@class": "PotentialSite", "@version": "0.9.12", "specie": "Cl", "distance": 3.6540533137106697, "potential": 0.29169999999999163, "pc_potential": null}, {"@module": "pydefect.corrections.efnv_correction", "@class": "PotentialSite", "@version": "0.9.12", "specie": "Cl", "distance": 6.751775164848276, "potential": 0.31759999999999877, "pc_potential": -0.05222329639510747}, {"@module": "pydefect.corrections.efnv_correction", "@class": "PotentialSite", "@version": "0.9.12", "specie": "Cl", "distance": 3.6593331493736234, "potential": 0.29070000000000107, "pc_potential": null}, {"@module": "pydefect.corrections.efnv_correction", "@class": "PotentialSite", "@version": "0.9.12", "specie": "Cl", "distance": 6.756380706316191, "potential": 0.3170999999999964, "pc_potential": -0.05232168172356434}, {"@module": "pydefect.corrections.efnv_correction", "@class": "PotentialSite", "@version": "0.9.12", "specie": "Cl", "distance": 8.87566533665216, "potential": 0.35429999999999495, "pc_potential": -0.09842591234072848}, {"@module": "pydefect.corrections.efnv_correction", "@class": "PotentialSite", "@version": "0.9.12", "specie": "Cl", "distance": 6.757331375119229, "potential": 0.3170999999999964, "pc_potential": -0.05226207291752509}, {"@module": "pydefect.corrections.efnv_correction", "@class": "PotentialSite", "@version": "0.9.12", "specie": "Cl", "distance": 8.8727403620584, "potential": 0.3532999999999902, "pc_potential": -0.0984711868633917}, {"@module": "pydefect.corrections.efnv_correction", "@class": "PotentialSite", "@version": "0.9.12", "specie": "Cl", "distance": 10.585231151952302, "potential": 0.35360000000000014, "pc_potential": -0.12361688621665894}, {"@module": "pydefect.corrections.efnv_correction", "@class": "PotentialSite", "@version": "0.9.12", "specie": "Cl", "distance": 8.871796934707001, "potential": 0.35379999999999256, "pc_potential": -0.0984603614935062}, {"@module": "pydefect.corrections.efnv_correction", "@class": "PotentialSite", "@version": "0.9.12", "specie": "Cl", "distance": 6.7579753370895705, "potential": 0.3183999999999969, "pc_potential": -0.0522911283913672}, {"@module": "pydefect.corrections.efnv_correction", "@class": "PotentialSite", "@version": "0.9.12", "specie": "Cl", "distance": 8.875384895622975, "potential": 0.3532999999999902, "pc_potential": -0.09845362777738176}, {"@module": "pydefect.corrections.efnv_correction", "@class": "PotentialSite", "@version": "0.9.12", "specie": "Cl", "distance": 6.75231350570725, "potential": 0.3177999999999912, "pc_potential": -0.05222152725794773}, {"@module": "pydefect.corrections.efnv_correction", "@class": "PotentialSite", "@version": "0.9.12", "specie": "Cl", "distance": 3.661014652107937, "potential": 0.2927999999999997, "pc_potential": null}, {"@module": "pydefect.corrections.efnv_correction", "@class": "PotentialSite", "@version": "0.9.12", "specie": "Cl", "distance": 6.755607079696455, "potential": 0.3158999999999992, "pc_potential": -0.05222647589132102}, {"@module": "pydefect.corrections.efnv_correction", "@class": "PotentialSite", "@version": "0.9.12", "specie": "Cl", "distance": 3.6641140749611134, "potential": 0.2930999999999955, "pc_potential": null}, {"@module": "pydefect.corrections.efnv_correction", "@class": "PotentialSite", "@version": "0.9.12", "specie": "Cl", "distance": 6.7455541472378195, "potential": 0.316599999999994, "pc_potential": -0.05250635452926534}, {"@module": "pydefect.corrections.efnv_correction", "@class": "PotentialSite", "@version": "0.9.12", "specie": "Cl", "distance": 8.88146790826166, "potential": 0.3575999999999908, "pc_potential": -0.09845738243558602}, {"@module": "pydefect.corrections.efnv_correction", "@class": "PotentialSite", "@version": "0.9.12", "specie": "Cl", "distance": 6.759556819361445, "potential": 0.3166999999999973, "pc_potential": -0.052516124900012395}, {"@module": "pydefect.corrections.efnv_correction", "@class": "PotentialSite", "@version": "0.9.12", "specie": "Cl", "distance": 3.6721685916869964, "potential": 0.29290000000000305, "pc_potential": null}, {"@module": "pydefect.corrections.efnv_correction", "@class": "PotentialSite", "@version": "0.9.12", "specie": "Cl", "distance": 6.755516386293405, "potential": 0.3166999999999973, "pc_potential": -0.05239574299873313}, {"@module": "pydefect.corrections.efnv_correction", "@class": "PotentialSite", "@version": "0.9.12", "specie": "Cl", "distance": 3.6633886453280655, "potential": 0.29240000000000066, "pc_potential": null}], "defect_coords": [0.0, 0.0, 0.0], "defect_region": {"@module": "pydefect.corrections.defect_region", "@class": "HalfMaxFaceDistanceDefectRegion", "@version": "0.9.12", "sample_radius_ratio": 1.0}}